twigy.cpython-36m-x86_64-linux-gnu.so
twigy-0.0.1.dist-info/top_level.txt
twigy-0.0.1.dist-info/WHEEL
twigy-0.0.1.dist-info/RECORD
twigy-0.0.1.dist-info/LICENSE
twigy-0.0.1.dist-info/METADATA
twigy.libs/libboost_system-194cb802.so.1.66.0
