Metadata-Version: 2.1
Name: twigy
Version: 0.0.1
Summary: Fast C++ implementation of decision tree and random forest classifiers with python bindings.
Home-page: https://github.com/christophmeyer/twigy
Author: Christoph Meyer
Author-email: christophmeyer87@gmail.com
License: UNKNOWN
Platform: UNKNOWN
Classifier: Programming Language :: Python :: 3
Classifier: Programming Language :: C++
Classifier: License :: OSI Approved :: MIT License
Classifier: Development Status :: 3 - Alpha
Classifier: Topic :: Scientific/Engineering :: Artificial Intelligence
Requires-Python: >=3.6
